SoukReqs/SoukReqs.py
SoukReqs/__init__.py
soukreqs-0.1.0.dist-info/METADATA
soukreqs-0.1.0.dist-info/WHEEL
soukreqs-0.1.0.dist-info/top_level.txt
soukreqs-0.1.0.dist-info/RECORD
