Metadata-Version: 2.4
Name: SoukReqs
Version: 0.1.0
Requires-Dist: requests
